<?xml version="1.0" encoding="utf-8" ?>
<configuration>
	<WatchFile Mode="Auto" />

	<SuggestImageDownloader Enabled="False" />
	
	<AppSource NewsUrl="https://github.com/NikolayXHD/Notifications/archive/master.zip" />
	
	<ImageLocations EnabledGroups="xlhq;dev" >

		<Directory Group="prod" Path="D:\Distrib\games\mtg\Mtgdb.Pictures\LQ" />
		<Directory Group="prod" Path="D:\Distrib\games\mtg\Mtgdb.Pictures\MQ" Zoom="True" />
		<Directory Group="prod" Path="D:\games\Mtgdb.Gui\images\Artworks" Art="True" ReadMetadataFromAttributes="False" />

		<Directory Group="dev" Zoom="False" Path="D:\Distrib\games\mtg\Gatherer.Original" />
		<Directory Group="dev" Zoom="True"  Path="D:\Distrib\games\mtg\Gatherer.Preprocessed" />
		<Directory Group="dev" Zoom="Any"   Path="D:\Distrib\games\mtg\Patch" />
		
		<Directory Group="xlhq" Zoom="Any"               Exclude="100DPI;100 DPI;200DPI;200 DPI;Crops" Path="D:\Distrib\games\mtg\Mega\XLHQ" />
		<Directory Group="xlhq" Zoom="Any" Set="DD3_DVD"                                               Path="D:\Distrib\games\mtg\Mega\XLHQ\DDA - Duel Decks%3a Anthology\DVD-EN Cards 300DPI" />
		<Directory Group="xlhq" Zoom="Any" Set="DD3_EVG"                                               Path="D:\Distrib\games\mtg\Mega\XLHQ\DDA - Duel Decks%3a Anthology\EVG-EN Cards 300DPI" />
		<Directory Group="xlhq" Zoom="Any" Set="DD3_GVL"                                               Path="D:\Distrib\games\mtg\Mega\XLHQ\DDA - Duel Decks%3a Anthology\GVL-EN Cards 300DPI" />
		<Directory Group="xlhq" Zoom="Any" Set="DD3_JVC"                                               Path="D:\Distrib\games\mtg\Mega\XLHQ\DDA - Duel Decks%3a Anthology\JVC-EN Cards 300DPI" />
		
		<Directory Group="xlhq" Zoom="Any"               Exclude="100DPI;100 DPI;200DPI;200 DPI;Crops" Path="D:\Distrib\games\mtg\Mega\XLHQ\Digital Sets" />
		<Directory Group="xlhq" Zoom="Any"               Exclude="100DPI;100 DPI;200DPI;200 DPI;Crops" Path="D:\Distrib\games\mtg\Mega\XLHQ\Digital Tokens" />
		<Directory Group="xlhq" Zoom="Any" Set="MPS_AKH" Exclude="100DPI;100 DPI;200DPI;200 DPI;Crops" Path="D:\Distrib\games\mtg\Mega\XLHQ\Masterpiece Series\Amonkhet Invocations" />
		<Directory Group="xlhq" Zoom="Any" Set="MPS"     Exclude="100DPI;100 DPI;200DPI;200 DPI;Crops" Path="D:\Distrib\games\mtg\Mega\XLHQ\Masterpiece Series\Kaladesh Inventions" />
		<Directory Group="xlhq" Zoom="Any" Set="EXP"     Exclude="100DPI;100 DPI;200DPI;200 DPI;Crops" Path="D:\Distrib\games\mtg\Mega\XLHQ\Masterpiece Series\Zendikar Expeditions" />
		<Directory Group="xlhq" Zoom="Any"               Exclude="100DPI;100 DPI;200DPI;200 DPI;Crops" Path="D:\Distrib\games\mtg\Mega\XLHQ\Promos" />
		<Directory Group="xlhq" Zoom="Any"               Exclude="100DPI;100 DPI;200DPI;200 DPI;Crops" Path="D:\Distrib\games\mtg\Mega\XLHQ\Promos\Pre-Release Promos" />
		<Directory Group="xlhq" Zoom="Any" Set="VMA"                                                   Path="D:\Distrib\games\mtg\Mega\XLHQ\Other\Vintage Champs 300DPI" />

		<Directory Group="xlhq" Zoom="Any"                 Path="D:\Distrib\games\mtg\XLHQ-Sets-Torrent.Unpacked" />
		<Directory Group="xlhq" Zoom="Any" Set="MMA"       Path="D:\Distrib\games\mtg\XLHQ-Sets-Torrent.Unpacked\MM1" />
		<Directory Group="xlhq" Zoom="Any" Set="RQS;ITP"   Path="D:\Distrib\games\mtg\XLHQ-Sets-Torrent.Unpacked\I2P" />
		<Directory Group="xlhq" Zoom="Any" Set="NMS"       Path="D:\Distrib\games\mtg\XLHQ-Sets-Torrent.Unpacked\NEM" />
		<Directory Group="xlhq" Zoom="Any" Set="CST"       Path="D:\Distrib\games\mtg\XLHQ-Sets-Torrent.Unpacked\CTD" />
		<Directory Group="xlhq" Zoom="Any" Set="CON"       Path="D:\Distrib\games\mtg\XLHQ-Sets-Torrent.Unpacked\CFX" />
		<Directory Group="xlhq" Zoom="Any" Set="CON"       Path="D:\Distrib\games\mtg\XLHQ-Sets-Torrent.Unpacked\CFX Extras" />
		<Directory Group="xlhq" Zoom="Any" Set="CON"       Path="D:\Distrib\games\mtg\XLHQ-Sets-Torrent.Unpacked\CFX Tokens" />
		<Directory Group="xlhq" Zoom="Any" Set="MD1"       Path="D:\Distrib\games\mtg\XLHQ-Sets-Torrent.Unpacked\MED" />

		<Directory Group="xlhq" Zoom="Any"                 Path="D:\Distrib\games\mtg\XLHQ Promos" />
		<Directory Group="xlhq" Zoom="Any" Set="pDRC"      Path="D:\Distrib\games\mtg\XLHQ Promos\Convention Promos\DragonCon" />
		<Directory Group="xlhq" Zoom="Any" Set="pMEI"      Path="D:\Distrib\games\mtg\XLHQ Promos\Convention Promos\www.magicthegathering.com" />
		<Directory Group="xlhq" Zoom="Any" Set="MGB"       Path="D:\Distrib\games\mtg\XLHQ Promos\Major Set Variants\Multiverse Box Set" />
		<Directory Group="xlhq" Zoom="Any" Set="pPOD"      Path="D:\Distrib\games\mtg\XLHQ Promos\Major Set Variants\Portal Demogame" />
		<Directory Group="xlhq" Zoom="Any" Set="S00"       Path="D:\Distrib\games\mtg\XLHQ Promos\Major Set Variants\Starter 2000 Sampler" />
		<Directory Group="xlhq" Zoom="Any" Set="pSUS"      Path="D:\Distrib\games\mtg\XLHQ Promos\Major Set Variants\Summer Magic (Partial)" />
		<Directory Group="xlhq" Zoom="Any" Set="10E"       Path="D:\Distrib\games\mtg\XLHQ Promos\Major Set Variants\Tenth Edition Alternate Foils (Partial)" />
		<Directory Group="xlhq" Zoom="Any" Set="pMEI"      Path="D:\Distrib\games\mtg\XLHQ Promos\Media Inserts" />
		<Directory Group="xlhq" Zoom="Any" Set="pHHO"      Path="D:\Distrib\games\mtg\XLHQ Promos\Other\Happy Holidays" />
		<Directory Group="xlhq" Zoom="Any" Set="pMEI"      Path="D:\Distrib\games\mtg\XLHQ Promos\Other\Resale Reward" />
		<Directory Group="xlhq" Zoom="Any" Set="pCEL"      Path="D:\Distrib\games\mtg\XLHQ Promos\Other\Richard Garfield" />
		<Directory Group="xlhq" Zoom="Any" Set="pWOS"      Path="D:\Distrib\games\mtg\XLHQ Promos\Other\WotC Online Store" />
		<Directory Group="xlhq" Zoom="Any" Set="s99"       Path="D:\Distrib\games\mtg\XLHQ Promos\Oversized\6x9\Starter" />
		<Directory Group="xlhq" Zoom="Any" Set="8ED"       Path="D:\Distrib\games\mtg\XLHQ Promos\Oversized\Boxtoppers\Eighth Edition" />
		<Directory Group="xlhq" Zoom="Any" Set="8ED"       Path="D:\Distrib\games\mtg\XLHQ Promos\Oversized\Boxtoppers\Eighth Edition Promos" />
		<Directory Group="xlhq" Zoom="Any" Set="9ED"       Path="D:\Distrib\games\mtg\XLHQ Promos\Oversized\Boxtoppers\Ninth Edition" />
		<Directory Group="xlhq" Zoom="Any" Set="CMD"       Path="D:\Distrib\games\mtg\XLHQ Promos\Oversized\Commanders\Commander 2011 Launch Party" />
		<Directory Group="xlhq" Zoom="Any" Set="AVR"       Path="D:\Distrib\games\mtg\XLHQ Promos\Oversized\Commanders\Helvault" />
		<Directory Group="xlhq" Zoom="Any" Set="VMA"       Path="D:\Distrib\games\mtg\XLHQ Promos\Oversized\Vintage Championship" />
		<Directory Group="xlhq" Zoom="Any" Set="pMPR"      Path="D:\Distrib\games\mtg\XLHQ Promos\Oversized\Magic Player Rewards" />
		<Directory Group="xlhq" Zoom="Any" Set="pMEI"      Path="D:\Distrib\games\mtg\XLHQ Promos\Set Promos\Duels of the Planeswalkers Reward Cards" />
		<Directory Group="xlhq" Zoom="Any" Set="pMEI"      Path="D:\Distrib\games\mtg\XLHQ Promos\Set Promos\Buy-a-Box" />
		<Directory Group="xlhq" Zoom="Any" Set="pMGD"      Path="D:\Distrib\games\mtg\XLHQ Promos\Set Promos\Game Day" />
		<Directory Group="xlhq" Zoom="Any" Set="pMEI"      Path="D:\Distrib\games\mtg\XLHQ Promos\Set Promos\Holiday Gift Box" />
		<Directory Group="xlhq" Zoom="Any" Set="pMEI"      Path="D:\Distrib\games\mtg\XLHQ Promos\Set Promos\Intro Packs" />
		<Directory Group="xlhq" Zoom="Any" Set="DD2"       Path="D:\Distrib\games\mtg\XLHQ Promos\Set Promos\Jace vs Chandra Anime" />
		<Directory Group="xlhq" Zoom="Any" Set="pPRE"      Path="D:\Distrib\games\mtg\XLHQ Promos\Set Promos\Prerelease" />
		<Directory Group="xlhq" Zoom="Any" Set="pREL"      Path="D:\Distrib\games\mtg\XLHQ Promos\Set Promos\Release and Launch Party\2003" />
		<Directory Group="xlhq" Zoom="Any" Set="pREL"      Path="D:\Distrib\games\mtg\XLHQ Promos\Set Promos\Release and Launch Party\2004" />
		<Directory Group="xlhq" Zoom="Any" Set="pREL"      Path="D:\Distrib\games\mtg\XLHQ Promos\Set Promos\Release and Launch Party\2005" />
		<Directory Group="xlhq" Zoom="Any" Set="pREL"      Path="D:\Distrib\games\mtg\XLHQ Promos\Set Promos\Release and Launch Party\2006" />
		<Directory Group="xlhq" Zoom="Any" Set="pREL"      Path="D:\Distrib\games\mtg\XLHQ Promos\Set Promos\Release and Launch Party\2007" />
		<Directory Group="xlhq" Zoom="Any" Set="pLPA"      Path="D:\Distrib\games\mtg\XLHQ Promos\Set Promos\Release and Launch Party\2008" />
		<Directory Group="xlhq" Zoom="Any" Set="pLPA"      Path="D:\Distrib\games\mtg\XLHQ Promos\Set Promos\Release and Launch Party\2009" />
		<Directory Group="xlhq" Zoom="Any" Set="pLPA"      Path="D:\Distrib\games\mtg\XLHQ Promos\Set Promos\Release and Launch Party\2010" />
		<Directory Group="xlhq" Zoom="Any" Set="pLPA"      Path="D:\Distrib\games\mtg\XLHQ Promos\Set Promos\Release and Launch Party\2011" />
		<Directory Group="xlhq" Zoom="Any" Set="pLPA"      Path="D:\Distrib\games\mtg\XLHQ Promos\Set Promos\Release and Launch Party\2012" />
		<Directory Group="xlhq" Zoom="Any" Set="pLPA"      Path="D:\Distrib\games\mtg\XLHQ Promos\Set Promos\Release and Launch Party\2013" />
		<Directory Group="xlhq" Zoom="Any" Set="pLPA"      Path="D:\Distrib\games\mtg\XLHQ Promos\Set Promos\Release and Launch Party\2014" />
		<Directory Group="xlhq" Zoom="Any" Set="pLPA"      Path="D:\Distrib\games\mtg\XLHQ Promos\Set Promos\Release and Launch Party\2015" />
		<Directory Group="xlhq" Zoom="Any" Set="DTK"       Path="D:\Distrib\games\mtg\XLHQ Promos\Set Promos\Tarkir Dragonfury" />
		<Directory Group="xlhq" Zoom="Any" Set="FRF_UGIN"  Path="D:\Distrib\games\mtg\XLHQ Promos\Set Promos\Ugin's Fate" />
		<Directory Group="xlhq" Zoom="Any" Set="FEM"       Path="D:\Distrib\games\mtg\XLHQ Promos\Tokens\Duelist Fallen Empires Tokens" />
		<Directory Group="xlhq" Zoom="Any" Set="pFNM"      Path="D:\Distrib\games\mtg\XLHQ Promos\Tokens\FNM" />
		<Directory Group="xlhq" Zoom="Any" Set="AVR"       Path="D:\Distrib\games\mtg\XLHQ Promos\Tokens\Helvault" />
		<Directory Group="xlhq" Zoom="Any" Set="pJGP"      Path="D:\Distrib\games\mtg\XLHQ Promos\Tokens\Judge" />
		<Directory Group="xlhq" Zoom="Any" Set="pARL"      Path="D:\Distrib\games\mtg\XLHQ Promos\Tokens\League" />
		<Directory Group="xlhq" Zoom="Any" Set="pMPR"      Path="D:\Distrib\games\mtg\XLHQ Promos\Tokens\Magic Player Rewards" />
		<Directory Group="xlhq" Zoom="Any" Set="CSP"       Path="D:\Distrib\games\mtg\XLHQ Promos\Tokens\Release Events" />
		<Directory Group="xlhq" Zoom="Any" Set="TSP"       Path="D:\Distrib\games\mtg\XLHQ Promos\Tokens\Time Spiral Bonus Program" />
		<Directory Group="xlhq" Zoom="Any" Set="p15A"      Path="D:\Distrib\games\mtg\XLHQ Promos\Tournament and Program Promos\15th Anniversary" />
		<Directory Group="xlhq" Zoom="Any" Set="pALP"      Path="D:\Distrib\games\mtg\XLHQ Promos\Tournament and Program Promos\APAC Lands" />
		<Directory Group="xlhq" Zoom="Any" Set="pARL"      Path="D:\Distrib\games\mtg\XLHQ Promos\Tournament and Program Promos\Arena League" />
		<Directory Group="xlhq" Zoom="Any" Set="pCMP"      Path="D:\Distrib\games\mtg\XLHQ Promos\Tournament and Program Promos\Champs" />
		<Directory Group="xlhq" Zoom="Any" Set="pLGM"      Path="D:\Distrib\games\mtg\XLHQ Promos\Tournament and Program Promos\DCI Legend" />
		<Directory Group="xlhq" Zoom="Any" Set="pELP"      Path="D:\Distrib\games\mtg\XLHQ Promos\Tournament and Program Promos\Euro Lands" />
		<Directory Group="xlhq" Zoom="Any" Set="pFNM"      Path="D:\Distrib\games\mtg\XLHQ Promos\Tournament and Program Promos\Friday Night Magic" />
		<Directory Group="xlhq" Zoom="Any" Set="pGTW"      Path="D:\Distrib\games\mtg\XLHQ Promos\Tournament and Program Promos\Gateway and Wizards Play Network\2006" />
		<Directory Group="xlhq" Zoom="Any" Set="pGTW"      Path="D:\Distrib\games\mtg\XLHQ Promos\Tournament and Program Promos\Gateway and Wizards Play Network\2007" />
		<Directory Group="xlhq" Zoom="Any" Set="pGTW;pWPN" Path="D:\Distrib\games\mtg\XLHQ Promos\Tournament and Program Promos\Gateway and Wizards Play Network\2008" />
		<Directory Group="xlhq" Zoom="Any" Set="pWPN"      Path="D:\Distrib\games\mtg\XLHQ Promos\Tournament and Program Promos\Gateway and Wizards Play Network\2009" />
		<Directory Group="xlhq" Zoom="Any" Set="pWPN"      Path="D:\Distrib\games\mtg\XLHQ Promos\Tournament and Program Promos\Gateway and Wizards Play Network\2010" />
		<Directory Group="xlhq" Zoom="Any" Set="pWPN"      Path="D:\Distrib\games\mtg\XLHQ Promos\Tournament and Program Promos\Gateway and Wizards Play Network\2011" />
		<Directory Group="xlhq" Zoom="Any" Set="pWPN"      Path="D:\Distrib\games\mtg\XLHQ Promos\Tournament and Program Promos\Gateway and Wizards Play Network\2012" />
		<Directory Group="xlhq" Zoom="Any" Set="pGPX"      Path="D:\Distrib\games\mtg\XLHQ Promos\Tournament and Program Promos\Grand Prix" />
		<Directory Group="xlhq" Zoom="Any" Set="pGRU"      Path="D:\Distrib\games\mtg\XLHQ Promos\Tournament and Program Promos\Guru" />
		<Directory Group="xlhq" Zoom="Any" Set="pJGP"      Path="D:\Distrib\games\mtg\XLHQ Promos\Tournament and Program Promos\Judge" />
		<Directory Group="xlhq" Zoom="Any" Set="pSUS"      Path="D:\Distrib\games\mtg\XLHQ Promos\Tournament and Program Promos\Junior Series" />
		<Directory Group="xlhq" Zoom="Any" Set="pMPR"      Path="D:\Distrib\games\mtg\XLHQ Promos\Tournament and Program Promos\Magic Player Rewards" />
		<Directory Group="xlhq" Zoom="Any" Set="pPRO"      Path="D:\Distrib\games\mtg\XLHQ Promos\Tournament and Program Promos\Pro Tour" />
		<Directory Group="xlhq" Zoom="Any" Set="pSUM"      Path="D:\Distrib\games\mtg\XLHQ Promos\Tournament and Program Promos\Summer of Magic" />
		<Directory Group="xlhq" Zoom="Any" Set="p2HG"      Path="D:\Distrib\games\mtg\XLHQ Promos\Tournament and Program Promos\Two-Headed Giant" />
		<Directory Group="xlhq" Zoom="Any" Set="pWCQ"      Path="D:\Distrib\games\mtg\XLHQ Promos\Tournament and Program Promos\World Magic Cup Qualifiers" />
		<Directory Group="xlhq" Zoom="Any" Set="pWOR"      Path="D:\Distrib\games\mtg\XLHQ Promos\Tournament and Program Promos\Worlds" />

		<!-- non-set codes -->
			<!-- 
			
			E:\Distrib\games\mtg\Mega\XLHQ
			Foreign Sets
			Other
				CAL97 300DPI
				CAL98 300DPI
				Testprints 300DPI
			Promos / PTD - Pro Tour Decks
				PT96-01
				...
				PT96-08
			WCD - World Championship Decks
				WC00-01
					WC00-01 300DPI
				..
				WC99-04
			-->
		
		<!-- Not mapped
		
		D:\Distrib\games\mtg\XLHQ Promos
		
		"D:\Distrib\games\mtg\XLHQ Promos\Tournament and Program Promos\Magic Premiere Store"
		"D:\Distrib\games\mtg\XLHQ Promos\Tournament and Program Promos\Dengeki Character Festival"
		"D:\Distrib\games\mtg\XLHQ Promos\Tokens\Magic Tenth Anniversary"
		"D:\Distrib\games\mtg\XLHQ Promos\Set Promos\Prerelease Pack Promos"
		"D:\Distrib\games\mtg\XLHQ Promos\Set Promos\Hero's Path"
		"D:\Distrib\games\mtg\XLHQ Promos\Set Promos\Duels of the Planeswalkers Reward Cards"
		"D:\Distrib\games\mtg\XLHQ Promos\Oversized\6x9\Arena"
		"D:\Distrib\games\mtg\XLHQ Promos\Oversized\6x9\Armada"
		"D:\Distrib\games\mtg\XLHQ Promos\Oversized\6x9\Caravan Tours 1995"
		"D:\Distrib\games\mtg\XLHQ Promos\Oversized\6x9\Duelist"
		"D:\Distrib\games\mtg\XLHQ Promos\Oversized\6x9\InQuest"
		"D:\Distrib\games\mtg\XLHQ Promos\Oversized\6x9\Microprose"
		"D:\Distrib\games\mtg\XLHQ Promos\Oversized\6x9\Release Events"
		"D:\Distrib\games\mtg\XLHQ Promos\Oversized\6x9\Scrye"
		"D:\Distrib\games\mtg\XLHQ Promos\Other\Schemes - Promotional"
		"D:\Distrib\games\mtg\XLHQ Promos\Other\Planes - Promotional"
		"D:\Distrib\games\mtg\XLHQ Promos\Other\DCI Tournament Center"
		"D:\Distrib\games\mtg\XLHQ Promos\Digital\Astral"
		"D:\Distrib\games\mtg\XLHQ Promos\Digital\Dreamcast"
		"D:\Distrib\games\mtg\XLHQ Promos\Extras\Card Pack Supplement"
		"D:\Distrib\games\mtg\XLHQ Promos\Extras\Dragon's Maze Achievement Cards"
		"D:\Distrib\games\mtg\XLHQ Promos\Extras\Dragon's Maze Guild Cards"
		"D:\Distrib\games\mtg\XLHQ Promos\Extras\Duels of the Planeswalkers 2012"
		"D:\Distrib\games\mtg\XLHQ Promos\Extras\Guru Book"
		"D:\Distrib\games\mtg\XLHQ Promos\Extras\Instinct"
		"D:\Distrib\games\mtg\XLHQ Promos\Extras\Japanese Sixth Anniversary"
		"D:\Distrib\games\mtg\XLHQ Promos\Extras\Pro Player Cards"
		"D:\Distrib\games\mtg\XLHQ Promos\Extras\Ravnica Guild Magnets"
		"D:\Distrib\games\mtg\XLHQ Promos\Extras\The Duelist"
		"D:\Distrib\games\mtg\XLHQ Promos\Extras\Time Spiral Art Cards"
		"D:\Distrib\games\mtg\XLHQ Promos\Extras\WotC Poker Deck"
		"D:\Distrib\games\mtg\XLHQ Promos\Convention Promos\Japanese Sixth Anniversary"
		"D:\Distrib\games\mtg\XLHQ Promos\Convention Promos\SDCC"
		
		-->
		
	</ImageLocations>
	
	<ImageCache CacheCapacity ="1000" />

	<ImageSources>
		<QualityGroup Quality="Art" TargetDirectory="D:\Distrib\games\mtg\Artwork" FileListUrl="https://mega.nz/#F!mgY1SSga!iP67fkG5mHQT23uYXwdP5g">
			<MegaDir Url="https://mega.nz/#F!39B0xRqL!QRyz9vbrroXflw7pOWda6Q" />
		</QualityGroup>
		
		<QualityGroup Quality="LQ" TargetDirectory="D:\Distrib\games\mtg\Mtgdb.Pictures\LQ" FileListUrl="https://mega.nz/#F!Jp1wETwQ!CL2o0x_C-y2rpiiGBGQfsA">
			<MegaDir Subdir="RIX"        Url="https://mega.nz/#F!p8dn3QxT!Suqk5bp_aepdhhzz8UGZFQ" />
			<MegaDir Subdir="E02"        Url="https://mega.nz/#F!RscS3YwT!YveBXu0u4jwkM5JzmK8byw" />
			<MegaDir Subdir="UST"        Url="https://mega.nz/#F!t010iLRL!FtbFVRVplWIfOct1uYx08w" />
			<MegaDir Subdir="DDT"        Url="https://mega.nz/#F!JllkDLaY!C6bDRfnC0TuaxiuVtMtdqA" />
			<MegaDir Subdir="IMA"        Url="https://mega.nz/#F!dk1CVZ7Q!nLxMb-u75oxf7fCZdfJZEg" />
			<MegaDir Subdir="2ED"        Url="https://mega.nz/#F!ZhtzzTjQ!UyL_Q0DMoZv8E0iq1OHv3g" />
			<MegaDir Subdir="3ED"        Url="https://mega.nz/#F!Yp83WJTY!QE8NumcSO7GmnVdzOCDI3Q" />
			<MegaDir Subdir="4ED"        Url="https://mega.nz/#F!0llHQQwD!K8fkaZTv7Ro1xzfgOi6YKg" />
			<MegaDir Subdir="5DN"        Url="https://mega.nz/#F!J8cywIDC!K41Z6JUZPYA7gY3o2QGtTQ" />
			<MegaDir Subdir="5ED"        Url="https://mega.nz/#F!0o8UURzT!9MdGWH9eI5CYAYMMFqzh8w" />
			<MegaDir Subdir="6ED"        Url="https://mega.nz/#F!YtdWUJyB!e05KA8w4K2EpPcRYcNd8RQ" />
			<MegaDir Subdir="7ED"        Url="https://mega.nz/#F!5wlVEIjQ!QpwrLq6iZjEODkM-ZhEqeQ" />
			<MegaDir Subdir="8ED"        Url="https://mega.nz/#F!8hsAnaZb!uu-WbwbLWChRCRXjd1NE4A" />
			<MegaDir Subdir="9ED"        Url="https://mega.nz/#F!okkinaKQ!4UiaIABatoJrW_hMkIpr0A" />
			<MegaDir Subdir="10E"        Url="https://mega.nz/#F!NtFCRCqJ!3v07C7vHK4ghwkH7kpdukg" />
			<MegaDir Subdir="AER"        Url="https://mega.nz/#F!Q0VjnLZS!fp0yo3AhmreBxrNGf4V3dQ" />
			<MegaDir Subdir="AKH"        Url="https://mega.nz/#F!ZlsnECgb!zJQHND2UjhS129_FLDzFvg" />
			<MegaDir Subdir="ALA"        Url="https://mega.nz/#F!Jg8zSarC!eq7NWJ0g-x8xcL15pAYK9Q" />
			<MegaDir Subdir="ALL"        Url="https://mega.nz/#F!BwVwVDzS!2YGTMNyc8vi4YIC_2QZmBw" />
			<MegaDir Subdir="APC"        Url="https://mega.nz/#F!NxMRCZ4T!T2RG2kLL8mWeLqS5eufPyw" />
			<MegaDir Subdir="ARB"        Url="https://mega.nz/#F!xxV0SByS!zqwczhCfQPrhaKFYf-AXXA" />
			<MegaDir Subdir="ARC"        Url="https://mega.nz/#F!I0d21BhI!OMwF3WUPtMArGaYejM6R4g" />
			<MegaDir Subdir="ARN"        Url="https://mega.nz/#F!9x9HWILS!6q7LzJ37aBNaH-5eYfBuCg" />
			<MegaDir Subdir="ATH"        Url="https://mega.nz/#F!4sEW2JxL!1qZUr_6vvXEUV2_NsnVy2Q" />
			<MegaDir Subdir="ATQ"        Url="https://mega.nz/#F!8otFjKaI!cVyzTrRJN1thXin2gtYpiQ" />
			<MegaDir Subdir="AVR"        Url="https://mega.nz/#F!gl82SDAQ!3z_EGx8FNrAKHtAfNpBNhA" />
			<MegaDir Subdir="BFZ"        Url="https://mega.nz/#F!Aw9FiSia!XQKwlNrWMeDGBflUiddmAg" />
			<MegaDir Subdir="BNG"        Url="https://mega.nz/#F!MwUyiaRA!U4uI6ohkL9R5Uwpl8vMfyw" />
			<MegaDir Subdir="BOK"        Url="https://mega.nz/#F!E0UmCRbD!L0LLqqkHn5U30X9A8x72Mw" />
			<MegaDir Subdir="BRB"        Url="https://mega.nz/#F!d8sTGTyb!cv2Uc8yRB2XBT1pCF3YpWQ" />
			<MegaDir Subdir="BTD"        Url="https://mega.nz/#F!Yxtj1SpI!iWkvBs31NFBNmv90_LDsxA" />
			<MegaDir Subdir="C13"        Url="https://mega.nz/#F!Ztl13JhS!lC_rmAxoYCTDxQnVQS1VgA" />
			<MegaDir Subdir="C14"        Url="https://mega.nz/#F!I8cnzCAQ!Vb6ipZcBSAONtN5UKgXqAA" />
			<MegaDir Subdir="C15"        Url="https://mega.nz/#F!IslymTBS!w1JCgRA2h8y30TMHXOVS7Q" />
			<MegaDir Subdir="C16"        Url="https://mega.nz/#F!Rp0BUJjb!MEYln6G8LlQH7N_grXY_gA" />
			<MegaDir Subdir="C17"        Url="https://mega.nz/#F!plliXQYZ!mrxxojMNZvFbF9chPRGSZA" />
			<MegaDir Subdir="CED"        Url="https://mega.nz/#F!4gEAAJAS!Oh6AhY-hy0CevQlnhR9qHw" />
			<MegaDir Subdir="CEI"        Url="https://mega.nz/#F!M5lSHZCA!NqbeHM4Mv-pg5s86dGSCyQ" />
			<MegaDir Subdir="CHK"        Url="https://mega.nz/#F!xwkTzaYL!5q93pX2Cs-nIeCHE-2dvyw" />
			<MegaDir Subdir="CHR"        Url="https://mega.nz/#F!JklDwQpS!JEd-5wAsWNGqjj6XIjV_YQ" />
			<MegaDir Subdir="CM1"        Url="https://mega.nz/#F!0sNgDCCb!vHxowKURMqTp1mtn14CnEw" />
			<MegaDir Subdir="CMA"        Url="https://mega.nz/#F!8xtizAAb!3k66NktXCzvZZIxloxpI0A" />
			<MegaDir Subdir="CMD"        Url="https://mega.nz/#F!0gEmEQLD!qHK_qasXx0sUMuMGTVoS6g" />
			<MegaDir Subdir="CN2"        Url="https://mega.nz/#F!AwECnYJB!yAndWtvu3JGZ_qG8jZqPxw" />
			<MegaDir Subdir="CNS"        Url="https://mega.nz/#F!sg1lTYAB!4G7lK0zCFKvZuySJJXVhrA" />
			<MegaDir Subdir="CON escape" Url="https://mega.nz/#F!dkcDjYaJ!aiipttvkNxwFXDtyDLy2YQ" />
			<MegaDir Subdir="CP1"        Url="https://mega.nz/#F!EsMEzBQK!inlw4yKmbHwPOLqcna6i9Q" />
			<MegaDir Subdir="CP2"        Url="https://mega.nz/#F!d51HyJwD!iFCDezENh9ezFfTmlD_IiQ" />
			<MegaDir Subdir="CP3"        Url="https://mega.nz/#F!x9EhCIpa!qVAf0ZfezWfyI9jrVgCwIw" />
			<MegaDir Subdir="CSP"        Url="https://mega.nz/#F!01d1HQJK!6OWbjBAl7MjOGvQRnGnRcQ" />
			<MegaDir Subdir="CST"        Url="https://mega.nz/#F!dw1zTRga!PAxLSaL5t544L-DYdOY4Qw" />
			<MegaDir Subdir="DD2"        Url="https://mega.nz/#F!khknQZoD!brpqaJaVznVKuH48t_Ihgw" />
			<MegaDir Subdir="DD3_DVD"    Url="https://mega.nz/#F!w48FxYIR!LrhGvvA8AIzaDoZ7hv7vYg" />
			<MegaDir Subdir="DD3_EVG"    Url="https://mega.nz/#F!dodCBTZb!-AvVEfSM5YGMy1xXKtIVfg" />
			<MegaDir Subdir="DD3_GVL"    Url="https://mega.nz/#F!Qp1FHCQD!mbTtBMqaJ1wDVRXzzQl8dg" />
			<MegaDir Subdir="DD3_JVC"    Url="https://mega.nz/#F!YttwRCIQ!zPHDfDHbKN6L5WyWaT9caw" />
			<MegaDir Subdir="DDC"        Url="https://mega.nz/#F!VwckyBYK!r_37vckeuw3fNDyPzwCzbA" />
			<MegaDir Subdir="DDD"        Url="https://mega.nz/#F!poc2zTTI!yJYdBtSe5q7WeqgUfXjGgA" />
			<MegaDir Subdir="DDE"        Url="https://mega.nz/#F!Q8kSxChS!zndottbEUzz2vg1UBazINg" />
			<MegaDir Subdir="DDF"        Url="https://mega.nz/#F!ll1ngZpZ!wvKiNQ73yOCUwNC-9ji_oQ" />
			<MegaDir Subdir="DDG"        Url="https://mega.nz/#F!thc1HKZT!bQGyEa6bgDQZ-4JqL0Kwgw" />
			<MegaDir Subdir="DDH"        Url="https://mega.nz/#F!8lMz1arT!Ut4FUyFG_ECz459ALAppBw" />
			<MegaDir Subdir="DDI"        Url="https://mega.nz/#F!wxdVxSiY!vgl3hTX7g6zSYNjYnqAwqg" />
			<MegaDir Subdir="DDJ"        Url="https://mega.nz/#F!c1NRUKjT!ycE8nOX9q7ly_MbHpTbjig" />
			<MegaDir Subdir="DDK"        Url="https://mega.nz/#F!QwklyIaL!59r0VTAKsW71Lxu9wBBoVw" />
			<MegaDir Subdir="DDL"        Url="https://mega.nz/#F!Q9cT0DDY!7Yy8eN3Cp2JwO-kPm9mwEg" />
			<MegaDir Subdir="DDM"        Url="https://mega.nz/#F!N5cy3QiA!oHB5l_gUQ_VxwGEj30GZhg" />
			<MegaDir Subdir="DDN"        Url="https://mega.nz/#F!wl8CBBJZ!8KF1hKrwYaoa8UCBsc8H0w" />
			<MegaDir Subdir="DDO"        Url="https://mega.nz/#F!108DDbBA!-3WPE36X06XCyHmbl5K5Og" />
			<MegaDir Subdir="DDP"        Url="https://mega.nz/#F!00EylI5T!SZnFYmHqKP_cw1OAiFoSwA" />
			<MegaDir Subdir="DDQ"        Url="https://mega.nz/#F!Rh12iCqa!ULCejXCJXyFQX_mqG9ryPQ" />
			<MegaDir Subdir="DDR"        Url="https://mega.nz/#F!5wMXyZBZ!rKJ26ejj71o_KRgKRA_awg" />
			<MegaDir Subdir="DDS"        Url="https://mega.nz/#F!w00jUQyL!95WHocD8YKD__OK4MyMqcA" />
			<MegaDir Subdir="DGM"        Url="https://mega.nz/#F!8ksgjZTK!M9t5u3oiksxHTBgQbrd1HA" />
			<MegaDir Subdir="DIS"        Url="https://mega.nz/#F!ll0WwAIb!xjdlozwscd5JVlihYoVwtA" />
			<MegaDir Subdir="DKA"        Url="https://mega.nz/#F!I4lzxRAL!LBoedDoAng7vYMCXeQGYeQ" />
			<MegaDir Subdir="DKM"        Url="https://mega.nz/#F!NhclCbqD!2Ywil79Tn91sFF4SinxwSg" />
			<MegaDir Subdir="DPA"        Url="https://mega.nz/#F!1sEAULQD!_RWc-q2ivl-ceOrSR_0IkA" />
			<MegaDir Subdir="DRB"        Url="https://mega.nz/#F!44VSlRAB!SRk_mdevMByQp6Al0c4-4Q" />
			<MegaDir Subdir="DRK"        Url="https://mega.nz/#F!BwEBDbgS!rTNZAjncA9zzTgTeIUJP1A" />
			<MegaDir Subdir="DST"        Url="https://mega.nz/#F!E01xAAhR!_FQv2ZDFMnfYT4CHxxmX2w" />
			<MegaDir Subdir="DTK"        Url="https://mega.nz/#F!cw9jEDRQ!QxIj7HzSxW-PBtq1-P-8wQ" />
			<MegaDir Subdir="E01"        Url="https://mega.nz/#F!t9sGHJoY!Ah7s4I5CeP8nJd8AoK9oRA" />
			<MegaDir Subdir="EMA"        Url="https://mega.nz/#F!Q10F2TpC!WPQiwYqgEn-otTNlgRGkgw" />
			<MegaDir Subdir="EMN"        Url="https://mega.nz/#F!9pdn2IAY!3zaLQD9Nm781bn3QVrQ0fg" />
			<MegaDir Subdir="EVE"        Url="https://mega.nz/#F!FwUWRYDZ!KRoDZ3wZ8ZOCSiiBGtsGVQ" />
			<MegaDir Subdir="EVG"        Url="https://mega.nz/#F!MllhAACa!NsVNuRsVeMGr4d-3GMU59Q" />
			<MegaDir Subdir="EXO"        Url="https://mega.nz/#F!QsdFWBIB!zRZa1MItqMeCpqotYvmnlg" />
			<MegaDir Subdir="EXP"        Url="https://mega.nz/#F!4tUxzQ4A!suvvhvSGS7HF4SOSImH04g" />
			<MegaDir Subdir="FEM"        Url="https://mega.nz/#F!EokinayB!77oqfDHWM4Og7EneO8VExA" />
			<MegaDir Subdir="FRF"        Url="https://mega.nz/#F!dgljBKZD!z_ty1FeIRxOB0tbv2btvsw" />
			<MegaDir Subdir="FRF_UGIN"   Url="https://mega.nz/#F!BwVChRKC!IfTSIffx3fgigfFO8bKB1A" />
			<MegaDir Subdir="FUT"        Url="https://mega.nz/#F!s48RnKQY!3vwo9c4BrY5yYZJvRLdjTg" />
			<MegaDir Subdir="GPT"        Url="https://mega.nz/#F!c0cEgBCY!dr0wMSRJxO8luNCVQSDWaQ" />
			<MegaDir Subdir="GTC"        Url="https://mega.nz/#F!Rx1D0IiS!LyPh5Km4SO--LgGR64rieQ" />
			<MegaDir Subdir="H09"        Url="https://mega.nz/#F!hldCgAqB!0UopeA8cONdzTV3vqKxWaQ" />
			<MegaDir Subdir="HML"        Url="https://mega.nz/#F!Y0twEZCa!h2EvDzEiOG5ttWVSERGBgw" />
			<MegaDir Subdir="HOP"        Url="https://mega.nz/#F!A8kEGZ7a!HkMH0aJgkMoV9AOMJDDFvg" />
			<MegaDir Subdir="HOU"        Url="https://mega.nz/#F!48VGGIIB!2i4zgkxJaodAVAeW7EkJwA" />
			<MegaDir Subdir="ICE"        Url="https://mega.nz/#F!tgsHSIqI!fwJmP-zkwOC33vWfrD_Dyg" />
			<MegaDir Subdir="INV"        Url="https://mega.nz/#F!0wtTUTiK!b_M3ZpAkLPzvcQZylI0TiA" />
			<MegaDir Subdir="ISD"        Url="https://mega.nz/#F!Qp0GjDgB!oef77s1TJmYbYq7N7R0pwQ" />
			<MegaDir Subdir="ITP"        Url="https://mega.nz/#F!d8siRB7B!i8g9_RxrdGTC6AJGguBN3g" />
			<MegaDir Subdir="JOU"        Url="https://mega.nz/#F!1sF2GbSB!CJiVOPZ4P3Y8Qtn1yM0eDw" />
			<MegaDir Subdir="JUD"        Url="https://mega.nz/#F!9gME3BIa!rZIxZ29_KS2rYo8OefuP7A" />
			<MegaDir Subdir="KLD"        Url="https://mega.nz/#F!10thiDLA!ng7aUTxo7L1xaljIP5_39A" />
			<MegaDir Subdir="KTK"        Url="https://mega.nz/#F!VstTjQLT!7oFDcPZbLeef2YvRmL4igQ" />
			<MegaDir Subdir="LEA"        Url="https://mega.nz/#F!FpVzzbSL!ukvnGJOKVY7jYGddFdBMCQ" />
			<MegaDir Subdir="LEB"        Url="https://mega.nz/#F!9w9CAZ5Y!1ISRGDGqaf5_fSrv4sWScA" />
			<MegaDir Subdir="LEG"        Url="https://mega.nz/#F!R00QhC4I!MzsOzXJkb26w4lKwGoMDLw" />
			<MegaDir Subdir="LGN"        Url="https://mega.nz/#F!dg11FRCa!z5ekq1u0oCr4_M1rPvmqHQ" />
			<MegaDir Subdir="LRW"        Url="https://mega.nz/#F!UkMRgDyb!RscAbRZQod6namlpG-XOZw" />
			<MegaDir Subdir="M10"        Url="https://mega.nz/#F!8tU0ma7A!hhDYv9BmTJHc4gFKsROt1g" />
			<MegaDir Subdir="M11"        Url="https://mega.nz/#F!08lRhRhD!_awa3h0mTfCZh3QCEDHNgw" />
			<MegaDir Subdir="M12"        Url="https://mega.nz/#F!Y1NFWDbI!g0Rl3-tvx6N_-6VJKsWriQ" />
			<MegaDir Subdir="M13"        Url="https://mega.nz/#F!E9FyUZiQ!-xvKVp3DlebnVKZ5AYkmrg" />
			<MegaDir Subdir="M14"        Url="https://mega.nz/#F!5pkUTKwB!BdEeakV_hGNDDjgfrBU8xg" />
			<MegaDir Subdir="M15"        Url="https://mega.nz/#F!F8VAnIib!x4OxmGBGJOsH8gBQUG8AAQ" />
			<MegaDir Subdir="MBS"        Url="https://mega.nz/#F!8pkmlaZA!sBWZc1ISpk_2rTYIXfA4VA" />
			<MegaDir Subdir="MD1"        Url="https://mega.nz/#F!g5ERXDQD!wZL2RHHWv2XX1NQnjZp2UA" />
			<MegaDir Subdir="ME2"        Url="https://mega.nz/#F!FsEhXTRB!DthmMae9BjOwd6vrSjtNFQ" />
			<MegaDir Subdir="ME3"        Url="https://mega.nz/#F!FgsQHZ6T!r8B3qukFfxK8RQD0n4q2yg" />
			<MegaDir Subdir="ME4"        Url="https://mega.nz/#F!E1VSmKrD!K8Jb6OfmUkz-C1XFnaw3DQ" />
			<MegaDir Subdir="MED"        Url="https://mega.nz/#F!FkFkWZ7B!1KAAJ41ZZ9D5j3lcfiwnxQ" />
			<MegaDir Subdir="MGB"        Url="https://mega.nz/#F!k50UEJSb!bXGrE6xgr4zxqkrvjUPlaA" />
			<MegaDir Subdir="MIR"        Url="https://mega.nz/#F!d0UAyRxB!619DeqkXBB2eVO4JICDvvA" />
			<MegaDir Subdir="MM2"        Url="https://mega.nz/#F!4t1DwB4a!uWfc9QGlUAvIhP2pQYWllw" />
			<MegaDir Subdir="MM3"        Url="https://mega.nz/#F!g1MT2YoZ!sdTXMLz9qIXVrgZBhYiywg" />
			<MegaDir Subdir="MMA"        Url="https://mega.nz/#F!BltGVATA!XAX8sVqJB3lOIka_C_PeOA" />
			<MegaDir Subdir="MMQ"        Url="https://mega.nz/#F!hk8FibyT!sEyDFclOmSM0bqxaE6cBCw" />
			<MegaDir Subdir="MOR"        Url="https://mega.nz/#F!cpUjhLwI!qjFrsJ8Ah9rsrQ3u4Y8smw" />
			<MegaDir Subdir="MPS"        Url="https://mega.nz/#F!B8NEkAwA!iGAcgxLDnK4WACNUTsWZlg" />
			<MegaDir Subdir="MPS_AKH"    Url="https://mega.nz/#F!U9cGADpA!hDZkU61KAHlkuyBBt4oVOw" />
			<MegaDir Subdir="MRD"        Url="https://mega.nz/#F!hod1Wa6Q!P7vuvmcx4FP2I3LgNPxbRQ" />
			<MegaDir Subdir="NMS"        Url="https://mega.nz/#F!Fsti3IQQ!dXZuVvmrfONL4cBrOMgBSA" />
			<MegaDir Subdir="NPH"        Url="https://mega.nz/#F!A91EAAqT!yWHABsAFEusKB4SHGRM8ug" />
			<MegaDir Subdir="ODY"        Url="https://mega.nz/#F!Vs9HFaJC!WQbvFXFkcF8hpkuoWsoElQ" />
			<MegaDir Subdir="OGW"        Url="https://mega.nz/#F!YhFEmbDI!H3pUUArzrorUajDKth90Fw" />
			<MegaDir Subdir="ONS"        Url="https://mega.nz/#F!YtVyFKAY!xFkEwn9fY1lQwqFdXlkbMg" />
			<MegaDir Subdir="ORI"        Url="https://mega.nz/#F!4gsnybLa!YNLPWGRfjDd47P9ywbh2BA" />
			<MegaDir Subdir="p2HG"       Url="https://mega.nz/#F!N90AQQQS!OW2IOWcMmYWSMxJrz0N1fw" />
			<MegaDir Subdir="p15A"       Url="https://mega.nz/#F!15sXmYqZ!mDYd596PzGjCo1oDw-JYHg" />
			<MegaDir Subdir="pALP"       Url="https://mega.nz/#F!F0Eh3KrQ!MTjqS4AhHRDFt9mGBUYNsQ" />
			<MegaDir Subdir="pARL"       Url="https://mega.nz/#F!El9WBBqS!ODJiLalH05nOY0hlCoTwug" />
			<MegaDir Subdir="PC2"        Url="https://mega.nz/#F!U9c2yCSa!271Os9XzkeP2UrJxrKNBmw" />
			<MegaDir Subdir="PCA"        Url="https://mega.nz/#F!NsFjWbrQ!Y3ygZBwHKl6bcclEjBwjJg" />
			<MegaDir Subdir="pCEL"       Url="https://mega.nz/#F!k8c2lAzY!K3ZIK7QiZcuXKuKAeYvyAA" />
			<MegaDir Subdir="pCMP"       Url="https://mega.nz/#F!k0cwTA7B!-BVWBTyxfEYS--mG391cUA" />
			<MegaDir Subdir="PCY"        Url="https://mega.nz/#F!Fod2xJIJ!OpRgrBlgjBWKg-rMNUkIiA" />
			<MegaDir Subdir="PD2"        Url="https://mega.nz/#F!p01j1CSS!FIpJny07GsQaZXp5fa6-dA" />
			<MegaDir Subdir="PD3"        Url="https://mega.nz/#F!J5diWYyR!TqbUZcoduGrE4zMZRcj1IA" />
			<MegaDir Subdir="pDRC"       Url="https://mega.nz/#F!RoNTyRiR!csdVg0Xifhnbb7Vjx6gusA" />
			<MegaDir Subdir="pELP"       Url="https://mega.nz/#F!NxdC1RSQ!KOEg6bjzrZUnl-WpWrOTTg" />
			<MegaDir Subdir="pFNM"       Url="https://mega.nz/#F!YgFhVQhR!F6LrdblYQpWVfq48QumtBA" />
			<MegaDir Subdir="pGPX"       Url="https://mega.nz/#F!lxlUAAyL!WMD7IZJWVg2Em54jUniyMg" />
			<MegaDir Subdir="pGRU"       Url="https://mega.nz/#F!888hUDxI!coiqCdi8x1lfc5dQFziRDg" />
			<MegaDir Subdir="pGTW"       Url="https://mega.nz/#F!0k0FwSYA!8o-cmU1vjCWLqNhng0iGpQ" />
			<MegaDir Subdir="pHHO"       Url="https://mega.nz/#F!pw1TnLjC!Q9Frdqgoq9j1y9__o6g_SA" />
			<MegaDir Subdir="pJGP"       Url="https://mega.nz/#F!lgU2mDQQ!hfbKqj5Exbkkk9b9mptIsg" />
			<MegaDir Subdir="PLC"        Url="https://mega.nz/#F!4pkxRYTR!Lx9PeBjPrFhnWpIF46-CIg" />
			<MegaDir Subdir="pLGM"       Url="https://mega.nz/#F!sgNnXYab!P5bWnvhQJZfRFIiADZaArQ" />
			<MegaDir Subdir="pLPA"       Url="https://mega.nz/#F!l9MGnDBL!_T5SJqTt37Z31MowewhYeA" />
			<MegaDir Subdir="PLS"        Url="https://mega.nz/#F!t1NxHAiS!9D32q6eSMCPYNxE_aZi94g" />
			<MegaDir Subdir="pMEI"       Url="https://mega.nz/#F!clFkDbia!xGyeC9blm-pJEWkpuZyRXg" />
			<MegaDir Subdir="pMGD"       Url="https://mega.nz/#F!Aolz2KKK!afA8w1TYeBYYIo1NhmzDkw" />
			<MegaDir Subdir="pMPR"       Url="https://mega.nz/#F!Q9snGDQQ!YgShDTboTTeAs9ZHvIBIbQ" />
			<MegaDir Subdir="PO2"        Url="https://mega.nz/#F!w59gkZxT!bE873NRIoSPWgqqruGK3Og" />
			<MegaDir Subdir="POR"        Url="https://mega.nz/#F!ptEByB6T!38xL878RX-UxdDhBVtdmpw" />
			<MegaDir Subdir="pPOD"       Url="https://mega.nz/#F!l4MnDJhJ!5RFckff6r4_XH95IClkoSg" />
			<MegaDir Subdir="pPRE"       Url="https://mega.nz/#F!M01VgKyQ!2ioSXOx_HomZP7B1jODzCw" />
			<MegaDir Subdir="pPRO"       Url="https://mega.nz/#F!opkxHSKL!bWDsEgoIJReSMBvDdYK2eg" />
			<MegaDir Subdir="pREL"       Url="https://mega.nz/#F!dtlzBR4Y!2VXJubZ_GZyo_fjqZu3zhQ" />
			<MegaDir Subdir="pSUM"       Url="https://mega.nz/#F!ptsjjDjY!qM_1nBqgQpm_BobK79hEXw" />
			<MegaDir Subdir="pSUS"       Url="https://mega.nz/#F!B8s10JTT!I9DCJdGcZzkgWCFoXwcUPw" />
			<MegaDir Subdir="PTK"        Url="https://mega.nz/#F!990XxSQY!-OyuT188AXFUJQlELf_9tQ" />
			<MegaDir Subdir="pWCQ"       Url="https://mega.nz/#F!o11w1ASA!TMPIQsnACPSdr52v_PXKMA" />
			<MegaDir Subdir="pWOR"       Url="https://mega.nz/#F!E8cBiTjC!3DQwV8oaUkm_7C-3f8sR7g" />
			<MegaDir Subdir="pWOS"       Url="https://mega.nz/#F!M1dkyTLZ!YwJF4Tajb7FM7LZ0N5ui8w" />
			<MegaDir Subdir="pWPN"       Url="https://mega.nz/#F!xgsQUSCB!7YNxcyrCai4lBtUT-SfO5g" />
			<MegaDir Subdir="RAV"        Url="https://mega.nz/#F!wkUxVD6Q!wm6NZbt1r6fVKVBK8oJIng" />
			<MegaDir Subdir="ROE"        Url="https://mega.nz/#F!859yGLJR!rhL1KbVmNrrS7CKSezDF8A" />
			<MegaDir Subdir="RQS"        Url="https://mega.nz/#F!91UGBBwT!fpwkKV5OrG7XrXnS5O6RQA" />
			<MegaDir Subdir="RTR"        Url="https://mega.nz/#F!Rsc3kYbQ!A7GDzxXYlrJ2lDQDnUikPw" />
			<MegaDir Subdir="S00"        Url="https://mega.nz/#F!00EkAQiB!yE7Rgs6vYbplzOWh0VZJpw" />
			<MegaDir Subdir="S99"        Url="https://mega.nz/#F!FlUxmBDC!pqrjnBTv2PFfB_Qiz4UXfA" />
			<MegaDir Subdir="SCG"        Url="https://mega.nz/#F!cllzWCYY!U8-SdqFMLLzhP2c4IkQE4Q" />
			<MegaDir Subdir="SHM"        Url="https://mega.nz/#F!hptD0BBa!RlASZj2ORebqNFga5WW0RQ" />
			<MegaDir Subdir="SOI"        Url="https://mega.nz/#F!IlkXVIBC!6rgHq9wp9QOrbDqxN25b3Q" />
			<MegaDir Subdir="SOK"        Url="https://mega.nz/#F!ogMkhbhb!FPgjBjVwm0xE9MOLoAC2bQ" />
			<MegaDir Subdir="SOM"        Url="https://mega.nz/#F!d58mGTRC!0AzNlKOnY7Efi0FIW8jPyg" />
			<MegaDir Subdir="STH"        Url="https://mega.nz/#F!ph8FjSrL!UbuydIKKTeXb-yttNhcUVg" />
			<MegaDir Subdir="THS"        Url="https://mega.nz/#F!ltMyjQob!T1YoX5EQlLy-DAzYR2bMOA" />
			<MegaDir Subdir="TMP"        Url="https://mega.nz/#F!p4FBFTDb!nWeVec2T0POarOXRAimf9Q" />
			<MegaDir Subdir="TOR"        Url="https://mega.nz/#F!kx8AjbCA!3lYM4jAqspuEQL254xNHJg" />
			<MegaDir Subdir="TPR"        Url="https://mega.nz/#F!xlEGhKJI!IatDkJtJKDUY9ADQXt9gkw" />
			<MegaDir Subdir="TSB"        Url="https://mega.nz/#F!VklUFJLY!RYFY0P7PAvHOVuxMo-OVNg" />
			<MegaDir Subdir="TSP"        Url="https://mega.nz/#F!o91BhIwB!icuPKLWbME7PHCpqwuZoxw" />
			<MegaDir Subdir="UDS"        Url="https://mega.nz/#F!Uh0mRZwZ!soHGFyryUCNpMwKMTAFK6w" />
			<MegaDir Subdir="UGL"        Url="https://mega.nz/#F!401whbya!dIXuG8shRASYaO1u4WBLcQ" />
			<MegaDir Subdir="ULG"        Url="https://mega.nz/#F!Rh9h0ZwS!Ih96tM5X27D8vc1Ks50uEw" />
			<MegaDir Subdir="UNH"        Url="https://mega.nz/#F!RskgHIQK!kvATKud8IUv4pSQ1ThpXpA" />
			<MegaDir Subdir="USG"        Url="https://mega.nz/#F!9oFD1BxK!Jpil7POVP4X4asCzevyGEw" />
			<MegaDir Subdir="V09"        Url="https://mega.nz/#F!p010xTjS!SyBGTpEcCbowtY8q-CHARQ" />
			<MegaDir Subdir="V10"        Url="https://mega.nz/#F!clVkHIyT!jgoc8DbZlbYYujPvPyJ2HQ" />
			<MegaDir Subdir="V11"        Url="https://mega.nz/#F!48sUFZAJ!Po1o8vVcZ91q8F6j83PYXw" />
			<MegaDir Subdir="V12"        Url="https://mega.nz/#F!V90glSTJ!AdpdxbI4fWyE6wRCIzW8xw" />
			<MegaDir Subdir="V13"        Url="https://mega.nz/#F!450kSQSZ!keBf8_eIrjKvLqRWw83a1w" />
			<MegaDir Subdir="V14"        Url="https://mega.nz/#F!010CwTgY!SRPaTI9j8N-WUqu4f2YWTA" />
			<MegaDir Subdir="V15"        Url="https://mega.nz/#F!tttQiLST!RaR7diL9wa4BTEcn5IKvQA" />
			<MegaDir Subdir="V16"        Url="https://mega.nz/#F!8wMgRSxQ!vb-MbmS9fsfYkVfVilqYFw" />
			<MegaDir Subdir="VAN"        Url="https://mega.nz/#F!Z4MFhJDa!vq5oDQ-kC2Hlt7F1YCsM3g" />
			<MegaDir Subdir="VIS"        Url="https://mega.nz/#F!IxcmDa6T!TtTtMPfyEOGarX51siA3Sw" />
			<MegaDir Subdir="VMA"        Url="https://mega.nz/#F!NxN1gCwY!KoscvXi-FAiGWcaUclpRNw" />
			<MegaDir Subdir="W16"        Url="https://mega.nz/#F!9wMVXI4L!ZL089a2r7znw11OBrPEKow" />
			<MegaDir Subdir="W17"        Url="https://mega.nz/#F!Mp11zL4T!vgMLcTDodmtmGoOrTBcifQ" />
			<MegaDir Subdir="WTH"        Url="https://mega.nz/#F!Vk1TwJwZ!abG44tFNin4EOO9uN-6V5A" />
			<MegaDir Subdir="WWK"        Url="https://mega.nz/#F!V1EGyDCQ!tV30nBAJjFnfFQPRazjznA" />
			<MegaDir Subdir="XLN"        Url="https://mega.nz/#F!A1dyRbzb!1BuoYy0tZPKX7ZnowVZaVw" />
			<MegaDir Subdir="ZEN"        Url="https://mega.nz/#F!01MBxTCY!NcbAwOsA9pDqxAQ41jcFVA" />
		</QualityGroup>
		
		<QualityGroup Quality="MQ" TargetDirectory="D:\Distrib\games\mtg\Mtgdb.Pictures\MQ" FileListUrl="https://mega.nz/#F!M80UFbwI!oneHfFYU8YNvUYeWBD-AzA">
			<MegaDir Subdir="RIX"        Url="https://mega.nz/#F!shMGgJLI!HoaKBRM_yFutrOTPMcJXcw" />
			<MegaDir Subdir="E02"        Url="https://mega.nz/#F!10UljJAJ!lrTS2rZ6b4uBtpd_z8DqwA" />
			<MegaDir Subdir="UST"        Url="https://mega.nz/#F!J00zFZoL!aqYkjeOwZBNlx0Alkp9S5g" />
			<MegaDir Subdir="DDT"        Url="https://mega.nz/#F!M4VUgLID!MeAxX7ajdHyWQU-lozkHeA" />
			<MegaDir Subdir="IMA"        Url="https://mega.nz/#F!Q40yXKSY!-Z7LViz573etopQyicCL7w" />
			<MegaDir Subdir="2ED"        Url="https://mega.nz/#F!p00kjQwS!dcRBCI956eb1SZDlELRcHA" />
			<MegaDir Subdir="3ED"        Url="https://mega.nz/#F!ZtVDQJyQ!PfbWMOy0kBGtJVjPyldfbw" />
			<MegaDir Subdir="4ED"        Url="https://mega.nz/#F!kpsyCZbB!0CMTvvy8STJbiViFkRpKOw" />
			<MegaDir Subdir="5DN"        Url="https://mega.nz/#F!111A3Qpa!-e0kNr8AR2_RkZ-lyBTWug" />
			<MegaDir Subdir="5ED"        Url="https://mega.nz/#F!81dQ0Jyb!y07Wpi5B1ssiiLmViSI5ow" />
			<MegaDir Subdir="6ED"        Url="https://mega.nz/#F!Aw1DECCR!IeKp0iLDwHEj7tldQrU_RQ" />
			<MegaDir Subdir="7ED"        Url="https://mega.nz/#F!hksHyYiR!H8U6tUJ1YgBnoS7oUeQbiw" />
			<MegaDir Subdir="8ED"        Url="https://mega.nz/#F!w1NRgSQC!9IvyEHUQZAvaN9K5eegsrw" />
			<MegaDir Subdir="9ED"        Url="https://mega.nz/#F!sttXXZ5J!sRyWvwTF0LRGXnj45_CP_A" />
			<MegaDir Subdir="10E"        Url="https://mega.nz/#F!BwVFQSLY!apAiFZBiwiPM5RjdibPCIQ" />
			<MegaDir Subdir="AER"        Url="https://mega.nz/#F!wgMQADpJ!VjintzfWYJXXvw1ytkbdsg" />
			<MegaDir Subdir="AKH"        Url="https://mega.nz/#F!toVDxCIS!I30UAyqUjdp6eJDA6FPlJA" />
			<MegaDir Subdir="ALA"        Url="https://mega.nz/#F!txdCEJzB!YeI8ihHojAweVt6KFrbmJw" />
			<MegaDir Subdir="ALL"        Url="https://mega.nz/#F!5ltWWR7K!5uYu2-JcSy_0gfIusbJjyg" />
			<MegaDir Subdir="APC"        Url="https://mega.nz/#F!hh9iBKZQ!dOB8JYTCqvmHkW6MZlZI_w" />
			<MegaDir Subdir="ARB"        Url="https://mega.nz/#F!QlciCbCT!Gig4FlbDqoUuGHwAwg0dSg" />
			<MegaDir Subdir="ARC"        Url="https://mega.nz/#F!VxMGVJxA!wMabRlLjgcRMVXeS2kMehA" />
			<MegaDir Subdir="ARN"        Url="https://mega.nz/#F!VlkQQDqQ!orRj1a6a2uIksY6D_rlRQA" />
			<MegaDir Subdir="ATH"        Url="https://mega.nz/#F!ptdjXDrL!qCCxJjUlxFKyYQMQFid90w" />
			<MegaDir Subdir="ATQ"        Url="https://mega.nz/#F!8gV3AaST!VuPV__4UGOiEvSl_tf24_Q" />
			<MegaDir Subdir="AVR"        Url="https://mega.nz/#F!8gkUCa6L!RABIMheW7fsufhm42RXsBw" />
			<MegaDir Subdir="BFZ"        Url="https://mega.nz/#F!4x00VCwJ!nc_j60XR1fndj7g6Xz7AOw" />
			<MegaDir Subdir="BNG"        Url="https://mega.nz/#F!Fk1k3SYL!wZOGYml4uaQ1x1NWTyJAcQ" />
			<MegaDir Subdir="BOK"        Url="https://mega.nz/#F!AwMBiL7R!nrE8VQ59C_5LVAd7rtT1AA" />
			<MegaDir Subdir="BRB"        Url="https://mega.nz/#F!p98x3ZbK!k1oKvPl2z4nph10NLNHKMw" />
			<MegaDir Subdir="BTD"        Url="https://mega.nz/#F!Vt9ljZBZ!mFnzkenG_4G3UuoW8cUTdA" />
			<MegaDir Subdir="C13"        Url="https://mega.nz/#F!xp00gLCT!c8JeXkAWPg9RyMkaZuccHg" />
			<MegaDir Subdir="C14"        Url="https://mega.nz/#F!x0lQlIoT!PvF5kylkyc0eLr4Xky6Gew" />
			<MegaDir Subdir="C15"        Url="https://mega.nz/#F!NodQnI7K!TFtiL1e5GhpN_7Qem2OHWA" />
			<MegaDir Subdir="C16"        Url="https://mega.nz/#F!IoEijCgb!7NLL1FPvnGQw6gm65WhxpQ" />
			<MegaDir Subdir="C17"        Url="https://mega.nz/#F!htFXjJ6S!VkZZTtqQ2-BGVip5Rucwsg" />
			<MegaDir Subdir="CED"        Url="https://mega.nz/#F!ckUH2bSS!6ur8FwnChw5VupjE7rhkrA" />
			<MegaDir Subdir="CEI"        Url="https://mega.nz/#F!s4U3XAoJ!WzqbkCUowLt-FT8rVElkTw" />
			<MegaDir Subdir="CHK"        Url="https://mega.nz/#F!ZsU1xJBD!UfbUvX665XnK1j44aRNaWQ" />
			<MegaDir Subdir="CHR"        Url="https://mega.nz/#F!d58yFBib!WHXwOo8t__R53ZwkjA3xtQ" />
			<MegaDir Subdir="CM1"        Url="https://mega.nz/#F!cpUnVB7B!YJZTQ-3cEL4wkZcX2SxiIw" />
			<MegaDir Subdir="CMA"        Url="https://mega.nz/#F!E8tRgD7J!kkIOq-y43bvv09038SVk0g" />
			<MegaDir Subdir="CMD"        Url="https://mega.nz/#F!YpkHSawB!GENw3f2WUnIec0OLlfg3KA" />
			<MegaDir Subdir="CN2"        Url="https://mega.nz/#F!J5NWDLKa!1x1ne6p5vxEUAxQ02sF-5w" />
			<MegaDir Subdir="CNS"        Url="https://mega.nz/#F!8112jK5I!7eWSs7kj2Dw2IovWPgjJ8A" />
			<MegaDir Subdir="CON escape" Url="https://mega.nz/#F!8t0yxZ4b!KgJ_nCzk34KLbEZmytWk3A" />
			<MegaDir Subdir="CP1"        Url="https://mega.nz/#F!c891VJbA!uZ-3CHJmJvECLV1bJ_FHbw" />
			<MegaDir Subdir="CP2"        Url="https://mega.nz/#F!p9kCQT7J!WpSYkTlvvzvXtpp50VZmEA" />
			<MegaDir Subdir="CP3"        Url="https://mega.nz/#F!gldCDZaa!h9-Hu0ABsGxLA5oM52kDAw" />
			<MegaDir Subdir="CSP"        Url="https://mega.nz/#F!E9820IAK!WmFBuVMl3kJN8yM2XMLZPg" />
			<MegaDir Subdir="CST"        Url="https://mega.nz/#F!Y58FAYgB!Lfr4s2lS_O-1Jjp8R6JVAQ" />
			<MegaDir Subdir="DD2"        Url="https://mega.nz/#F!Rh8CxYjQ!ubNawpapmGd74AWh6Dm31w" />
			<MegaDir Subdir="DD3_DVD"    Url="https://mega.nz/#F!9xkTDDIJ!jzlC9-5NiOv7XZHDG6hdLw" />
			<MegaDir Subdir="DD3_EVG"    Url="https://mega.nz/#F!9h9XFCQD!DoaqE3N6oW0AvvfDZq7B3A" />
			<MegaDir Subdir="DD3_GVL"    Url="https://mega.nz/#F!thEgxAxI!N858yiK2oGkz_clAudIi0A" />
			<MegaDir Subdir="DD3_JVC"    Url="https://mega.nz/#F!Yhs3kZQB!YdZWw22OynYAsHo6CmhrVg" />
			<MegaDir Subdir="DDC"        Url="https://mega.nz/#F!w0sHyJaD!ZLsUK1bC6xq3LSp2AtcS1w" />
			<MegaDir Subdir="DDD"        Url="https://mega.nz/#F!s9sySBRK!FCmh25wUBQcjGniFYLYNZg" />
			<MegaDir Subdir="DDE"        Url="https://mega.nz/#F!k90z1J5T!if5HJuweb0T83Cm2z62C5A" />
			<MegaDir Subdir="DDF"        Url="https://mega.nz/#F!V0sVHATZ!Zl-2CD2874MdLlUBQTbfbQ" />
			<MegaDir Subdir="DDG"        Url="https://mega.nz/#F!hhkxBTrI!UkhE2QAZNtiYuDhQGKGZ8A" />
			<MegaDir Subdir="DDH"        Url="https://mega.nz/#F!tk90AASQ!Xm_K-FEVlqAhuUXPVtqMEQ" />
			<MegaDir Subdir="DDI"        Url="https://mega.nz/#F!xlkBXCRa!1RQdliQ9xV6iM9f80WbOmg" />
			<MegaDir Subdir="DDJ"        Url="https://mega.nz/#F!t4NFQbDR!UmWd0BxrcVjmR6KcY-KUMg" />
			<MegaDir Subdir="DDK"        Url="https://mega.nz/#F!wtsVlSqQ!s1fqWeFmg2nu8Ww-GcihxA" />
			<MegaDir Subdir="DDL"        Url="https://mega.nz/#F!dtsgWbhI!_uzAQBYEeJYkY16tjt5xiw" />
			<MegaDir Subdir="DDM"        Url="https://mega.nz/#F!d493TCRD!VKYBxBS03EEzF4YG-wFxmg" />
			<MegaDir Subdir="DDN"        Url="https://mega.nz/#F!t0E3HDLD!9RNLQIRnitZ-pIeP_zk8GA" />
			<MegaDir Subdir="DDO"        Url="https://mega.nz/#F!Zlk1zRzI!Ae98V6aawdcCrhG299Tu3g" />
			<MegaDir Subdir="DDP"        Url="https://mega.nz/#F!o0dxmRpT!z0sB-95qAiYIbQ7rcQbaIQ" />
			<MegaDir Subdir="DDQ"        Url="https://mega.nz/#F!k502xZZR!9yvjX6DY8lK1W8310GtxuQ" />
			<MegaDir Subdir="DDR"        Url="https://mega.nz/#F!N48ECDJa!owRJsL8pUVUQEr0nSJlrbw" />
			<MegaDir Subdir="DDS"        Url="https://mega.nz/#F!kkcSkT7Y!4bOMm4N26LSgX5P4mmOK1w" />
			<MegaDir Subdir="DGM"        Url="https://mega.nz/#F!Z0k1HDiA!owNADeNRQ8311JOF60IcJg" />
			<MegaDir Subdir="DIS"        Url="https://mega.nz/#F!19UHFCaC!5T_DOxBOC8-ZOH_SUHcpAA" />
			<MegaDir Subdir="DKA"        Url="https://mega.nz/#F!pp8SRL6B!1czIBO55OOPSGN7ECizTmw" />
			<MegaDir Subdir="DKM"        Url="https://mega.nz/#F!IsU1Dbwb!Hn4IfL4taH73p-Cne9WCLw" />
			<MegaDir Subdir="DPA"        Url="https://mega.nz/#F!g8FgkIjS!zzneCZHTddGrF0VTIswUGg" />
			<MegaDir Subdir="DRB"        Url="https://mega.nz/#F!15MR2SqL!cWt63cq4jv6BJB1pEPuCrQ" />
			<MegaDir Subdir="DRK"        Url="https://mega.nz/#F!hokFxDQA!U_ZF9EJGqBMO2b2vymYA0g" />
			<MegaDir Subdir="DST"        Url="https://mega.nz/#F!FpkxlSLS!_o7J1NAEpji--dtJ4m2DIA" />
			<MegaDir Subdir="DTK"        Url="https://mega.nz/#F!A98HFRRS!J19lI-mcuLhsbYGCAK7sVQ" />
			<MegaDir Subdir="E01"        Url="https://mega.nz/#F!Upt1VbYS!Lp75ZLSQuEi2KhZuZvORBg" />
			<MegaDir Subdir="EMA"        Url="https://mega.nz/#F!glUXja4S!Z9tMTgHFASmcY7ixO0aaOQ" />
			<MegaDir Subdir="EMN"        Url="https://mega.nz/#F!Fx9gXYhS!3hWaEZxBL7dOQ5A2uaSKVw" />
			<MegaDir Subdir="EVE"        Url="https://mega.nz/#F!dkk1UDzK!E-1Hu3zFXYLFaOlRZwpIoQ" />
			<MegaDir Subdir="EVG"        Url="https://mega.nz/#F!5xUGzDZI!L4lJyeVrkk39Qv1OhCuQCg" />
			<MegaDir Subdir="EXO"        Url="https://mega.nz/#F!hs8n2KJT!l5Z51ptNs4bFJNQf1i3l1A" />
			<MegaDir Subdir="EXP"        Url="https://mega.nz/#F!tsFxESJa!aN7Ug9HWpsvx1e7vhe1tPQ" />
			<MegaDir Subdir="FEM"        Url="https://mega.nz/#F!Ux1R3AaR!N8KLzCZYojy9jA2snYE8fQ" />
			<MegaDir Subdir="FRF"        Url="https://mega.nz/#F!xwUQDTzb!P5tFzqrPQ25OooVrkbE-Uw" />
			<MegaDir Subdir="FRF_UGIN"   Url="https://mega.nz/#F!JkEVnLJD!9_6qQBjqHsXgvWeLjGrVkw" />
			<MegaDir Subdir="FUT"        Url="https://mega.nz/#F!0xMzxSZB!kP3BwsCsa8bGj3Qby1KG-A" />
			<MegaDir Subdir="GPT"        Url="https://mega.nz/#F!JoVVBaBR!FKZD8FrTzbRp1ephkxupSQ" />
			<MegaDir Subdir="GTC"        Url="https://mega.nz/#F!AtdR0Q6R!P2BkvIqAY0U3DyzTfzqRKA" />
			<MegaDir Subdir="H09"        Url="https://mega.nz/#F!FxNXQIza!a-4w93YbWL01VEtrU1W9iw" />
			<MegaDir Subdir="HML"        Url="https://mega.nz/#F!t90XATYK!YSZy0dVUBjWw8FASb3pfkg" />
			<MegaDir Subdir="HOP"        Url="https://mega.nz/#F!5gUXhCBC!kW8DtUYfNSYR_ELLPKq_tw" />
			<MegaDir Subdir="HOU"        Url="https://mega.nz/#F!R9sCkZiJ!6Q2eAZ7f8MoNEtBvJsnonQ" />
			<MegaDir Subdir="ICE"        Url="https://mega.nz/#F!EkdV0CxI!wkraty2I8YmDjP0g5EkbQA" />
			<MegaDir Subdir="INV"        Url="https://mega.nz/#F!5htTxJ4Z!aofuL1swxEZazCK1Vpg4Iw" />
			<MegaDir Subdir="ISD"        Url="https://mega.nz/#F!B1dWgIAK!T_GPbDngLj8HwLZ6ycCEkg" />
			<MegaDir Subdir="ITP"        Url="https://mega.nz/#F!k99R3Awb!WDMgvKSoV7Y5_H4UC5VRSA" />
			<MegaDir Subdir="JOU"        Url="https://mega.nz/#F!Z19gEYwL!7l7Slq1yEW7uTaBsq2fhlw" />
			<MegaDir Subdir="JUD"        Url="https://mega.nz/#F!5t0WRJBT!_cjyIwcg--13c0HWziAjcw" />
			<MegaDir Subdir="KLD"        Url="https://mega.nz/#F!AsFzXaYQ!XRBJh3izvsrwYx1gseUiRQ" />
			<MegaDir Subdir="KTK"        Url="https://mega.nz/#F!15EAwIwJ!WxV5mLIKHrZJeEG4xWfF8Q" />
			<MegaDir Subdir="LEA"        Url="https://mega.nz/#F!stNEULLQ!H0Oa-ddNXUCSvAeO7CBn_Q" />
			<MegaDir Subdir="LEB"        Url="https://mega.nz/#F!swkmVKIL!CAwC3oKF76EhetkG1T2Frg" />
			<MegaDir Subdir="LEG"        Url="https://mega.nz/#F!8scFQAIJ!LB0hem_GHoaM--3bZriUdQ" />
			<MegaDir Subdir="LGN"        Url="https://mega.nz/#F!1odE2aYZ!rxJemgd3P49yf7kNbIqC2w" />
			<MegaDir Subdir="LRW"        Url="https://mega.nz/#F!Ql1wgaSQ!kuohKckJx6Semb_Aj1HrLg" />
			<MegaDir Subdir="M10"        Url="https://mega.nz/#F!xh11DT5Q!GMMX_LEKgdYsU-gOk-iHGw" />
			<MegaDir Subdir="M11"        Url="https://mega.nz/#F!I89RTRxJ!aTGiiMtCqfcYzLqx4W2IHw" />
			<MegaDir Subdir="M12"        Url="https://mega.nz/#F!hlMzmbQA!Ukzqut7kHEpDQa4cTGcj4Q" />
			<MegaDir Subdir="M13"        Url="https://mega.nz/#F!95UG1SKT!GZgPDK51W8MJnTcyiZMzgg" />
			<MegaDir Subdir="M14"        Url="https://mega.nz/#F!M4k0WBYJ!8dI1vrgAB2Lt7HzXQivhSg" />
			<MegaDir Subdir="M15"        Url="https://mega.nz/#F!ksUGCRbY!VOZqw60WKqs_xI5S2uPY1w" />
			<MegaDir Subdir="MBS"        Url="https://mega.nz/#F!N9cFXb5J!O2XaxokgGLW7zgP8YSZlIQ" />
			<MegaDir Subdir="MD1"        Url="https://mega.nz/#F!E11xmQgT!mMtG7muZzvu-fueQ4iF-OA" />
			<MegaDir Subdir="ME2"        Url="https://mega.nz/#F!541SCQoQ!Uv24SToznQFFuoUqZu_DoQ" />
			<MegaDir Subdir="ME3"        Url="https://mega.nz/#F!QhV3WBTL!DSA0SpH-Q7e8Z0nWILxfJA" />
			<MegaDir Subdir="ME4"        Url="https://mega.nz/#F!01EwCQzK!vKQRjFpMv83gsvCDUugZVg" />
			<MegaDir Subdir="MED"        Url="https://mega.nz/#F!F491RBjY!tQLepoUFVA7E8yUMdkgLEg" />
			<MegaDir Subdir="MGB"        Url="https://mega.nz/#F!Y58ATTTY!aNfLPNVJ2x1IPatM9inPZg" />
			<MegaDir Subdir="MIR"        Url="https://mega.nz/#F!sg1SHTJQ!0-iOMIQLBrGeSaf8YJkdpA" />
			<MegaDir Subdir="MM2"        Url="https://mega.nz/#F!IwFykITI!tEHkNW7y6TZu6nRMPWcJig" />
			<MegaDir Subdir="MM3"        Url="https://mega.nz/#F!4t0jzDiD!17SoRg34MwSt56nvO877yA" />
			<MegaDir Subdir="MMA"        Url="https://mega.nz/#F!5g9B3LCI!0cRh7OYVTrFuCx1lt86pYQ" />
			<MegaDir Subdir="MMQ"        Url="https://mega.nz/#F!RwcBkLBS!IFQSIYKuO1a6a_tfvsJyHA" />
			<MegaDir Subdir="MOR"        Url="https://mega.nz/#F!15MAEKaT!wJdA_NA5RPwZj8ibfi0EmQ" />
			<MegaDir Subdir="MPS"        Url="https://mega.nz/#F!lw12QRrA!VzK2hdblZ0zktobm0jo2kQ" />
			<MegaDir Subdir="MPS_AKH"    Url="https://mega.nz/#F!h582jCwA!_4k9R2rin39X5toVnzC0nA" />
			<MegaDir Subdir="MRD"        Url="https://mega.nz/#F!40N0HKiK!6vypyHl11sYtX3DkiaIWtA" />
			<MegaDir Subdir="NMS"        Url="https://mega.nz/#F!lpUkQTIY!YJkkK8flRa1mNybfGtg2qA" />
			<MegaDir Subdir="NPH"        Url="https://mega.nz/#F!9o1CkTZL!7Mq7yKjOWJAhO3kK8uRGFg" />
			<MegaDir Subdir="ODY"        Url="https://mega.nz/#F!Fh0GBJjB!F3WateQRwzjSdGugfXGfAQ" />
			<MegaDir Subdir="OGW"        Url="https://mega.nz/#F!x9M0UTSK!IfI00B0aIrzRiwbLFzNQdQ" />
			<MegaDir Subdir="ONS"        Url="https://mega.nz/#F!polViJ7Z!GsGGuHzYdtzbP0IQLvUhGg" />
			<MegaDir Subdir="ORI"        Url="https://mega.nz/#F!s5lmnTyC!aws953kbRR7oKFqP-BTNgg" />
			<MegaDir Subdir="p2HG"       Url="https://mega.nz/#F!I003CB4Y!Mpu00Yg37pb4ulxybidWUA" />
			<MegaDir Subdir="p15A"       Url="https://mega.nz/#F!wxFlECiQ!EC-VrSd8WSJo0rJ9vkGDNA" />
			<MegaDir Subdir="pALP"       Url="https://mega.nz/#F!4ok0xDhB!FBmJYd6FMmj4o5AHlFIwSg" />
			<MegaDir Subdir="pARL"       Url="https://mega.nz/#F!ghkGFAhJ!RCNHUYnrHStFQB6PfjbtUA" />
			<MegaDir Subdir="PC2"        Url="https://mega.nz/#F!V0NTAaYZ!g3og925PMZJbPbHsaJylQg" />
			<MegaDir Subdir="PCA"        Url="https://mega.nz/#F!Rt1lkSCZ!yc6pLSFyGoP45tsWoEAD_Q" />
			<MegaDir Subdir="pCEL"       Url="https://mega.nz/#F!sldUnKqJ!5giX86c77-ErzTcbKBLy6g" />
			<MegaDir Subdir="pCMP"       Url="https://mega.nz/#F!x8MDSSqT!xZKbZ2DEmlqRGbkpUYKsqg" />
			<MegaDir Subdir="PCY"        Url="https://mega.nz/#F!9tM1kagK!j7PhKyv6JsXFUHZvvVP8tQ" />
			<MegaDir Subdir="PD2"        Url="https://mega.nz/#F!81NCiT4J!QuOn7E29CXs69kUiJ7pLAQ" />
			<MegaDir Subdir="PD3"        Url="https://mega.nz/#F!l9VAzIAL!Jft1cwY5k2CTI1YGnz7ztg" />
			<MegaDir Subdir="pDRC"       Url="https://mega.nz/#F!UlNxzIoR!i7noB9UWrR156m9bRYetkw" />
			<MegaDir Subdir="pELP"       Url="https://mega.nz/#F!l01WiBzL!D1z5I4iYDr-3pT5Pm6v8Ow" />
			<MegaDir Subdir="pFNM"       Url="https://mega.nz/#F!t18BARiI!FoaAcSyhRnrbpau_4Vt4Mw" />
			<MegaDir Subdir="pGPX"       Url="https://mega.nz/#F!I8kVwD5Z!cRd0gdih9x8BKW8HSQJXUg" />
			<MegaDir Subdir="pGRU"       Url="https://mega.nz/#F!d4snHLQS!gdbP8IxLjBfsW5G3-xdW0w" />
			<MegaDir Subdir="pGTW"       Url="https://mega.nz/#F!FpN2wYaS!P1PnOycsh7ausCI-mRR0AA" />
			<MegaDir Subdir="pHHO"       Url="https://mega.nz/#F!YkUWyBiK!C_gWM9aB9InPZTcuW449Yg" />
			<MegaDir Subdir="pJGP"       Url="https://mega.nz/#F!99FCXSpC!B6_t6vqr-dpGfsNM9y0RQw" />
			<MegaDir Subdir="PLC"        Url="https://mega.nz/#F!t1sgxIZK!bLrzVMXcAWUhxDTIRagHig" />
			<MegaDir Subdir="pLGM"       Url="https://mega.nz/#F!0ps1VLgb!1S0hZyLCgRNLLo7GuBTtXg" />
			<MegaDir Subdir="pLPA"       Url="https://mega.nz/#F!s41lGTBR!J1hXewnHSYKZGYFM8MOCwg" />
			<MegaDir Subdir="PLS"        Url="https://mega.nz/#F!4o9SXKTC!HCTAIc8v7_NOSDAaEhJKdg" />
			<MegaDir Subdir="pMEI"       Url="https://mega.nz/#F!Uhdj2S5C!qj9I3Rs4n1GtaUlx7B0bHg" />
			<MegaDir Subdir="pMGD"       Url="https://mega.nz/#F!VhFmTDwA!4tlVHz2_RMtuhgeLYh4CXQ" />
			<MegaDir Subdir="pMPR"       Url="https://mega.nz/#F!F8kUGajZ!NEkW6EvUYmzJUHEgQ2m-wg" />
			<MegaDir Subdir="PO2"        Url="https://mega.nz/#F!E9sVRLBI!kV1YpDPcyW3wfZRPQ2fePw" />
			<MegaDir Subdir="POR"        Url="https://mega.nz/#F!d0UnxKJL!5jStt9KWOaECmPk64TKJVw" />
			<MegaDir Subdir="pPOD"       Url="https://mega.nz/#F!B5cXWRwK!bhuuWC2rpbzMGEtCtxIWyQ" />
			<MegaDir Subdir="pPRE"       Url="https://mega.nz/#F!8w9X1DDZ!uQDhgy-mbmbfOw6-LPjmEA" />
			<MegaDir Subdir="pPRO"       Url="https://mega.nz/#F!Zo8lCYoS!VVaFKQD32lWdgjXrSj5eMg" />
			<MegaDir Subdir="pREL"       Url="https://mega.nz/#F!Jsll0awA!0tJJ4nzHGAg88jH-w8SxaQ" />
			<MegaDir Subdir="pSUM"       Url="https://mega.nz/#F!ctNEgAAb!h_SzKgkPXDFUGiskOpqkmg" />
			<MegaDir Subdir="pSUS"       Url="https://mega.nz/#F!BkcWiYJa!QG_t5aLqKQz_QQfeSiSDAw" />
			<MegaDir Subdir="PTK"        Url="https://mega.nz/#F!IoFXzQKZ!tkt-XEEFo7eZIG7n-b01kA" />
			<MegaDir Subdir="pWCQ"       Url="https://mega.nz/#F!Y11WgQJD!IhqnCPZQT5t2X5u7lO9Cqw" />
			<MegaDir Subdir="pWOR"       Url="https://mega.nz/#F!AosDSIAA!w7DwtQk-bD1AFs-XojK43A" />
			<MegaDir Subdir="pWOS"       Url="https://mega.nz/#F!I5dCQC5D!ZX-6klVrZg8sUXdzhbbEzA" />
			<MegaDir Subdir="pWPN"       Url="https://mega.nz/#F!h4NUkAga!-PmCcK2ZtYslJ979EquJOQ" />
			<MegaDir Subdir="RAV"        Url="https://mega.nz/#F!I91l1CaJ!8c_1T1NYhCO6jJ-JyteePQ" />
			<MegaDir Subdir="ROE"        Url="https://mega.nz/#F!N19zVCqL!SPSZau_woW0vvQJJSjQ8fQ" />
			<MegaDir Subdir="RQS"        Url="https://mega.nz/#F!phMSkbBT!h1y-kEXozOZ7seVFYhplcw" />
			<MegaDir Subdir="RTR"        Url="https://mega.nz/#F!osV2SajD!WOKkoER8G-olqB67RM-Lqg" />
			<MegaDir Subdir="S00"        Url="https://mega.nz/#F!A0tgWSwT!u6yjawOfpqepfFQOv0mfEw" />
			<MegaDir Subdir="S99"        Url="https://mega.nz/#F!8hMFhDwB!zh6Yvurtx8DyYlE1SCQr2Q" />
			<MegaDir Subdir="SCG"        Url="https://mega.nz/#F!Fs1BjI6Y!no0cyTQUsJrEiB4I5q6M0w" />
			<MegaDir Subdir="SHM"        Url="https://mega.nz/#F!l4cBkb7J!h_iTCuTrLZ4KOyzRpRraXg" />
			<MegaDir Subdir="SOI"        Url="https://mega.nz/#F!AoNHQI5K!wUG6WWTZ4r8tnYsF4EdpZw" />
			<MegaDir Subdir="SOK"        Url="https://mega.nz/#F!otlG0LwD!wDIBvyv545viMy3B-7nDKQ" />
			<MegaDir Subdir="SOM"        Url="https://mega.nz/#F!co9i3A7a!54oaOrF3QfQewsSEUgnTCw" />
			<MegaDir Subdir="STH"        Url="https://mega.nz/#F!F8E0WL5Y!8zMF49E3udh2ctd91RyF8A" />
			<MegaDir Subdir="THS"        Url="https://mega.nz/#F!gos1TIZQ!299_B44vLD16bH3RGhaR-w" />
			<MegaDir Subdir="TMP"        Url="https://mega.nz/#F!hhlTEYhJ!xReIp2ZLUN4M2cIQLhUY2Q" />
			<MegaDir Subdir="TOR"        Url="https://mega.nz/#F!A98gjLqA!KjAtYbAVinktaUta1R0MzQ" />
			<MegaDir Subdir="TPR"        Url="https://mega.nz/#F!RldRGaRB!PcWwzPxPzZguVR3UX-ld_A" />
			<MegaDir Subdir="TSB"        Url="https://mega.nz/#F!EsVgxAwR!Oe8r2Vwk5lXZSXWnv-un5A" />
			<MegaDir Subdir="TSP"        Url="https://mega.nz/#F!l5klHAbY!mvumwbMlJm00YnPy7NY-aw" />
			<MegaDir Subdir="UDS"        Url="https://mega.nz/#F!oplFmQQK!sY1CMAUU2MvJEB2TGIPisQ" />
			<MegaDir Subdir="UGL"        Url="https://mega.nz/#F!J9sjVLCb!kLJhmFjIvTw0D9EHIIHXzQ" />
			<MegaDir Subdir="ULG"        Url="https://mega.nz/#F!dkUFBa4K!ANSgcvH6FtnBulA7SUy8Kw" />
			<MegaDir Subdir="UNH"        Url="https://mega.nz/#F!hkUX0aAA!hrVURLLhpzSj5IMcugiBmw" />
			<MegaDir Subdir="USG"        Url="https://mega.nz/#F!hhtRCKiC!7XfCmQpBORBllUHYRanA8g" />
			<MegaDir Subdir="V09"        Url="https://mega.nz/#F!R8UFCJBZ!O9N7g4jAJHVWH-qRZ-HpKA" />
			<MegaDir Subdir="V10"        Url="https://mega.nz/#F!Vo0g3TDT!OMvFufweUZ8hMzt6BTrijQ" />
			<MegaDir Subdir="V11"        Url="https://mega.nz/#F!tssB2L4T!vs2TYCH2uGQOB1FjGnt_bg" />
			<MegaDir Subdir="V12"        Url="https://mega.nz/#F!JkcFiK7Q!TRyoGZ93WIuYZ34AKFmD9w" />
			<MegaDir Subdir="V13"        Url="https://mega.nz/#F!4wkEWIJJ!kbHYHJbixsG88ccncSYa6Q" />
			<MegaDir Subdir="V14"        Url="https://mega.nz/#F!gx03lYgL!qXn73QdQL8cHngUcIupinA" />
			<MegaDir Subdir="V15"        Url="https://mega.nz/#F!l1EkATga!b_NyOxcY1JZha3OHR__g-g" />
			<MegaDir Subdir="V16"        Url="https://mega.nz/#F!Z8cznbQD!bzOnuLoBBPCh-sIrqCOivQ" />
			<MegaDir Subdir="VAN"        Url="https://mega.nz/#F!VotxwKgI!DtbpWPcja-NBvOLMz-YEeQ" />
			<MegaDir Subdir="VIS"        Url="https://mega.nz/#F!0gEUmCJS!vg41XnDQo7Y6FYpScDw6bQ" />
			<MegaDir Subdir="VMA"        Url="https://mega.nz/#F!R0ECDBrB!kSJ42YZd6rmeA0l-V3TMOg" />
			<MegaDir Subdir="W16"        Url="https://mega.nz/#F!E0lmQTbY!d6NPaoOmaAmQV40axzv3tg" />
			<MegaDir Subdir="W17"        Url="https://mega.nz/#F!dl0CXbSA!XRnE-Nwa8oe7-g2x6cBuZA" />
			<MegaDir Subdir="WTH"        Url="https://mega.nz/#F!041mzY5L!3NhACmAwB8jM8yr7qAtW5Q" />
			<MegaDir Subdir="WWK"        Url="https://mega.nz/#F!YllTiLrZ!rCKJENehWGp64cgZvq5Rqg" />
			<MegaDir Subdir="XLN"        Url="https://mega.nz/#F!Zk9lgR4b!WXQ8DXqhZnLA1BXohYEgqg" />
			<MegaDir Subdir="ZEN"        Url="https://mega.nz/#F!psdyEAyQ!kCX7dNpQI2PHQkkrOW1kfw" />
		</QualityGroup>
	</ImageSources>
	
</configuration>